{
  "id": "tudasbazis/bovitmenyek/divipasswords",
  "title": "DiviPasswords",
  "description": "Divi-kiegészítő, amellyel jelszóval védhetsz bármely Divi szekciót, sort, oszlopot vagy modult; a védett tartalom feloldásig teljesen eltűnik a DOM-ból.",
  "source": "@site/docs/tudasbazis/bovitmenyek/divipasswords.md",
  "sourceDirName": "tudasbazis/bovitmenyek",
  "slug": "/tudasbazis/bovitmenyek/divipasswords",
  "permalink": "/docs/tudasbazis/bovitmenyek/divipasswords",
  "draft": false,
  "unlisted": false,
  "editUrl": "https://github.com/hellowpio/hub.hellowp.io/blob/main/docs/tudasbazis/bovitmenyek/divipasswords.md",
  "tags": [],
  "version": "current",
  "frontMatter": {
    "title": "DiviPasswords",
    "description": "Divi-kiegészítő, amellyel jelszóval védhetsz bármely Divi szekciót, sort, oszlopot vagy modult; a védett tartalom feloldásig teljesen eltűnik a DOM-ból.",
    "sidebar_label": "DiviPasswords"
  },
  "sidebar": "tutorialSidebar",
  "previous": {
    "title": "Divi Toolbox",
    "permalink": "/docs/tudasbazis/bovitmenyek/divi-toolbox"
  },
  "next": {
    "title": "Dynamic.ooo - Dynamic Content for Elementor",
    "permalink": "/docs/tudasbazis/bovitmenyek/dynamic-ooo-dynamic-content-for-elementor"
  }
}